{
  "id": "ke-1774200060-tc-shipment-id",
  "type": "integration",
  "question": "What is the TC Shipment ID and how is it constructed? How do you join OP and Manhattan using it?",
  "answer": "The TC_SHIPMENT_ID is the cross-system key that links a customer order in OP to a shipment record in Manhattan WMS. Construction formula for customer orders (outbound): TC_SHIPMENT_ID = DC_ID(3 digits) + YYYY(4 digits) + MM(2 digits) + DD(2 digits) + load_num(4 digits, zero-padded) = 15 total characters. Example: 160202601220561 = DC 160 (Dothan/MD), date 2026-01-22, load number 0561. The date used is the LLR date (Load Label Release date), found in LOAD_DEPART_OP1F and LOAD_CLOS_CNTRL_BC2C. To find the LLR date and load number in OP: query LOAD_DEPART_OP1F and LOAD_CLOS_CNTRL_BC2C joining on div_part, llr_dt, and load_num. Cross-system join: Manhattan SHIPMENT.TC_SHIPMENT_ID (VARCHAR2) = constructed value from OP tables. In OPCIG database: DIV_MSTR_DI1D.fin_div_cd maps to WMSHUB.WM1D_WMS_DC_MSTR.dc_id (same value). Note: inbound ASN/PO shipments in Manhattan also have TC_SHIPMENT_ID populated but with a different format (DC_ID + MMDD + YYYY + seq); the YYYY+MMDD pattern above applies to outbound customer orders only.",
  "context": {
    "group": "cigwms-prod",
    "schemas": ["OP", "WMSHUB", "SE_DM", "MD_DM", "FE_DM"],
    "dcCodes": [],
    "systems": ["op", "wmshub", "manhattan"],
    "objects": ["SHIPMENT", "LOAD_DEPART_OP1F", "LOAD_CLOS_CNTRL_BC2C", "DIV_MSTR_DI1D", "WM1D_WMS_DC_MSTR"]
  },
  "tags": ["tc_shipment_id", "cross-system join", "op system", "manhattan", "load_num", "llr date", "load label release", "dc_id", "shipment id", "integration key"],
  "quality": 3,
  "source": "expert-provided",
  "capturedBy": "asrajag",
  "approved": true,
  "createdAt": "2026-03-21T00:00:00.000Z",
  "updatedAt": "2026-03-21T00:00:00.000Z"
}
